{"Jugador1": {"Construir": [], "Mover": [], "Reclutar": [{"Territorio": "Titotito", "Cantidad": 1}], "Comerciar": [], "Atacar": [{"Or\u00edgenes": {"Titotito": 1}, "Destino": "Mercado"}, {"Or\u00edgenes": {"Titotito": 1}, "Destino": "Siglo XXI"}, {"Or\u00edgenes": {"Titotito": 1}, "Destino": "Tintero"}, {"Or\u00edgenes": {"Titotito": 1}, "Destino": "Wade"}, {"Or\u00edgenes": {"Titotito": 1}, "Destino": "Tritonda"}, {"Or\u00edgenes": {"Titotito": 1}, "Destino": "Pomodoro"}], "Cesion": []}, "Jugador2": {"Construir": [], "Mover": [], "Reclutar": [{"Territorio": "Brifer", "Cantidad": 2}], "Comerciar": [], "Atacar": [{"Or\u00edgenes": {"Brifer": 1}, "Destino": "Anden"}, {"Or\u00edgenes": {"Brifer": 1}, "Destino": "Mandala"}, {"Or\u00edgenes": {"Brifer": 1}, "Destino": "Bubbles"}, {"Or\u00edgenes": {"Brifer": 1}, "Destino": "Vialia"}, {"Or\u00edgenes": {"Brifer": 1}, "Destino": "Limonar"}, {"Or\u00edgenes": {"Brifer": 1}, "Destino": "Benabu"}], "Cesion": [], "Dar Baja": []}, "Jugador3": {"Construir": [], "Mover": [], "Reclutar": [{"Territorio": "Gamle By", "Cantidad": 4}], "Comerciar": [], "Atacar": [{"Or\u00edgenes": {"Gamle By": 1}, "Destino": "Mombasa"}, {"Or\u00edgenes": {"Gamle By": 1}, "Destino": "Gold"}, {"Or\u00edgenes": {"Gamle By": 1}, "Destino": "Larios"}, {"Or\u00edgenes": {"Gamle By": 1}, "Destino": "Rocking"}, {"Or\u00edgenes": {"Gamle By": 1}, "Destino": "Periplo"}, {"Or\u00edgenes": {"Gamle By": 1}, "Destino": "Kali"}], "Cesion": []}, "Jugador4": {"Construir": [], "Mover": [], "Reclutar": [], "Comerciar": [], "Atacar": [{"Or\u00edgenes": {"Edoras": 1}, "Destino": "Pimpi"}, {"Or\u00edgenes": {"Edoras": 1}, "Destino": "Candado"}, {"Or\u00edgenes": {"Edoras": 1}, "Destino": "Skatepark"}, {"Or\u00edgenes": {"Edoras": 1}, "Destino": "Dominos"}, {"Or\u00edgenes": {"Edoras": 1}, "Destino": "Dundee"}], "Cesion": []}, "Jugador5": {"Construir": [], "Mover": [], "Reclutar": [{"Territorio": "Torrole", "Cantidad": 5}], "Comerciar": [], "Atacar": [{"Or\u00edgenes": {"Torrole": 1}, "Destino": "Merlo"}, {"Or\u00edgenes": {"Torrole": 1}, "Destino": "Juan"}, {"Or\u00edgenes": {"Torrole": 1}, "Destino": "Sebastian"}, {"Or\u00edgenes": {"Torrole": 1}, "Destino": "Miguelito"}, {"Or\u00edgenes": {"Torrole": 1}, "Destino": "Chancla"}, {"Or\u00edgenes": {"Torrole": 1}, "Destino": "Verdes"}], "Cesion": []}, "Jugador6": {"Construir": [], "Mover": [], "Reclutar": [{"Territorio": "Jerusalen", "Cantidad": 3}], "Comerciar": [], "Atacar": [{"Or\u00edgenes": {"Jerusalen": 1}, "Destino": "Cremades"}, {"Or\u00edgenes": {"Jerusalen": 1}, "Destino": "Tejeringo"}, {"Or\u00edgenes": {"Jerusalen": 1}, "Destino": "Ancla"}, {"Or\u00edgenes": {"Jerusalen": 1}, "Destino": "Sta Gema"}, {"Or\u00edgenes": {"Jerusalen": 1}, "Destino": "Mafalda"}, {"Or\u00edgenes": {"Jerusalen": 1}, "Destino": "Vox"}], "Cesion": []}}